odoo/addons/ssi_project_code/README.rst
odoo/addons/ssi_project_code/__init__.py
odoo/addons/ssi_project_code/__manifest__.py
odoo/addons/ssi_project_code/models/__init__.py
odoo/addons/ssi_project_code/models/project_project.py
odoo/addons/ssi_project_code/static/description/icon.png
odoo/addons/ssi_project_code/views/project_project_views.xml
odoo14_addon_ssi_project_code-14.0.1.1.0.dist-info/METADATA
odoo14_addon_ssi_project_code-14.0.1.1.0.dist-info/WHEEL
odoo14_addon_ssi_project_code-14.0.1.1.0.dist-info/top_level.txt
odoo14_addon_ssi_project_code-14.0.1.1.0.dist-info/RECORD
