Metadata-Version: 2.1
Name: odoo14-addon-ssi-project-code
Version: 14.0.1.1.0
Summary: Project Code
Home-page: https://simetri-sinergi.id
Author: OpenSynergy Indonesia, PT. Simetri Sinergi Indonesia
License: LGPL-3
Platform: UNKNOWN
Classifier: Programming Language :: Python
Classifier: Framework :: Odoo
Classifier: Framework :: Odoo :: 14.0
Classifier: License :: OSI Approved :: GNU Lesser General Public License v3 (LGPLv3)
Requires-Python: >=3.6
Requires-Dist: odoo14-addon-ssi-project
Requires-Dist: odoo (<14.1dev,>=14.0a)
